LICENSE
MANIFEST.in
README
ego-boost
setup.py
ego_boost.egg-info/PKG-INFO
ego_boost.egg-info/SOURCES.txt
ego_boost.egg-info/dependency_links.txt
ego_boost.egg-info/requires.txt
ego_boost.egg-info/top_level.txt
egoboost/__init__.py
egoboost/cmdln.py
egoboost/runner.py
egoboost/stats.py
egoboost/storage.py
egoboost/utils.py