Metadata-Version: 1.0
Name: ego-boost
Version: 0.1.1
Summary: Package to track your module's download statistics
Home-page: http://pypi.python.org/pypi/ego-boost
Author: Sebastian Rahlf
Author-email: basti at redtoad dot de
License: MIT
Platform: UNKNOWN
Classifier: Development Status :: 4 - Beta
Classifier: Environment :: Console
Classifier: Intended Audience :: Developers
Classifier: License :: OSI Approved :: MIT License
Classifier: Operating System :: OS Independent
Classifier: Programming Language :: Python
Classifier: Topic :: System :: Archiving :: Packaging
Classifier: Topic :: System :: Logging
